module/QuantumOscillators.py
module/SaduQuantumFinance.py
module/__init__.py
saduquantumfinance-0.1.0.dist-info/METADATA
saduquantumfinance-0.1.0.dist-info/WHEEL
saduquantumfinance-0.1.0.dist-info/top_level.txt
saduquantumfinance-0.1.0.dist-info/RECORD
