Metadata-Version: 2.4
Name: SaduQuantumFinance
Version: 0.1.0
Summary: A package that deals with Quantum Finance, Provides plotting visuals
Author: SaduPostMagazine
Author-email: sadupostrivista@gmail.com
Classifier: Programming Language :: Python :: 3
Classifier: Intended Audience :: Developers
Dynamic: author
Dynamic: author-email
Dynamic: classifier
Dynamic: summary
